ascibar/__init__.py
ascibar/core.py
ascibar-0.1.0.dist-info/LICENSE
ascibar-0.1.0.dist-info/METADATA
ascibar-0.1.0.dist-info/WHEEL
ascibar-0.1.0.dist-info/top_level.txt
ascibar-0.1.0.dist-info/RECORD
