Metadata-Version: 2.1
Name: ascibar
Version: 0.1.0
Summary: A Lightweight Python library for creating customizable ASCII-based progress bars in terminal applications.
Home-page: https://github.com/mouhamaddev/ascibar
Author: mouhamaddev
Author-email: mouhamaddev04@gmail.com
Classifier: Programming Language :: Python :: 3
Classifier: License :: OSI Approved :: GNU General Public License v3 (GPLv3)
Classifier: Operating System :: OS Independent
Requires-Python: >=3.6
License-File: LICENSE
